{
"version":"1.0.0",
"message":"Please NEW Version Download\n‌ကြော်ငြာများကို ဖျယ်ရှားထားပါ\n All KAR အသစ်များ စုစည်းပြီး  \n အသစ်ထုတ်ထားပါတယ် ခေါင်းကြီးတို့။  \n  မြန်မာ ချောင်းရိုက် နဲ့ ဆယ်လီမ HDတွေ ထက်ထည့်ပေးထားလို့  \n  ခုပဲ အပ်ဒိတ် တင်လိုက်ပါ။",
"link":"https://play.google.com/store/apps/details?id=",
"state":"off",
"des":"မြန်မာနိုင်ငံမှာ နေသူများ video ကြည့်ရန် VPN ခံထားမို့ လိုအပ်ပါသည်။\n\n ကျေးဇူးပြု၍ VPN ခံပြီးဝင်ရောက်ပေးပါ မိတ်ဆွေ။\n\nစင်္ကာပူ  ၊ အမေရိကန် ၊ ဂျပန် ၊ ထိုင်း စသည့် နိုင်ငံများ နှင့် ချိတ်ဆက်ပေးပါခင်ဗျ၊၊၊ \nအာဘွား အရမ်းချစ်တယ်။ ",
"faninter":"",
"admob_Banner":"",
"admob_Inter":"",
"adstime":"5",
"apyar":[
{
"title":" ၁ ။ Dream Number 1 Formulas ",
"image":"https://i.ibb.co/r2XDfGPQ/20250330-152510.jpg",
"link":"https://zindown.github.io/showimg.html?img=https://i.ibb.co/1tS5D3m9/20250330-214303.png",
"type":"x"
 },  
 {
"title":" ၂ ။ Dream Number 2 Formulas ",
"image":"https://i.ibb.co/YFTs203D/20250330-151501.jpg",
"link":"https://zindown.github.io/showimg.html?img=https://i.ibb.co/chvBWygJ/20250330-214236.png",
"type":"x"
},  
 { 
  "title":"၃ ။ Dream Number 3 Formulas",
  "image":"https://i.ibb.co/VYp9W8ns/20250330-151700.jpg", 
  "link":"https://zindown.github.io/showimg.html?img=https://i.ibb.co/hFcRnjBz/20250330-214220.png", 
  "type":"x"
}, 
 { 
  "title":"၄ ။ Dream Number 4 Formulas ",
  "image":"https://i.ibb.co/twxKCnM5/20250330-151831.jpg", 
  "link":"https://zindown.github.io/showimg.html?img=https://i.ibb.co/pj4p38g5/20250330-214202.png", 
  "type":"x"
}, 
 { 
  "title":"၅ ။ Dream Number 5 Formulas ",
  "image":"https://i.ibb.co/7N6xj8yq/20250330-151956.jpg", 
  "link":"https://zindown.github.io/showimg.html?img=https://i.ibb.co/xK19F25t/20250330-214142.png", 
  "type":"x"
}, 
 { 
  "title":"၆ ။ Dream Number 6 Formulas ",
  "image":"https://i.ibb.co/C5YbNs5y/20250330-152042.jpg", 
  "link":"https://zindown.github.io/showimg.html?img=https://i.ibb.co/YFDTB9cy/20250330-214119.png", 
  "type":"x"
}, 
 { 
  "title":"၇ ။ Dream Number 7 Formulas ",
  "image":"https://i.ibb.co/hR8dVPK9/20250330-152116.jpg", 
  "link":"https://zindown.github.io/showimg.html?img=https://i.ibb.co/WNgpqfSw/20250330-214102.png", 
  "type":"x"
}, 
 { 
  "title":"၈ ။ Dream Number 8 Formulas ",
  "image":"https://i.ibb.co/KpBNx1Wv/20250330-152223.jpg", 
  "link":"https://zindown.github.io/showimg.html?img=https://i.ibb.co/7tDmHTL2/20250330-214042.png", 
  "type":"x"
}, 
 { 
  "title":"၉ ။ Dream Number 9 Formulas",
  "image":"https://i.ibb.co/hJrjbnJF/20250330-152314.jpg", 
  "link":"https://zindown.github.io/showimg.html?img=https://i.ibb.co/LXSZQTJc/20250330-214027.png", 
  "type":"x"
}, 
 { 
  "title":"၁၀ ။ Dream Number 10 Formulas",
  "image":"https://i.ibb.co/p6bc4jKv/20250330-152354.jpg", 
  "link":"https://zindown.github.io/showimg.html?img=https://i.ibb.co/1t963CqC/20250330-214010.png", 
  "type":"x"
}, 
{ 
 "title":"၅၅ ။ Dream Number 66 Formulas", 
 "image":"https://i.ibb.co/r2XDfGPQ/20250330-152510.jpg", 
  "link":"https://zindown.github.io/showimg.html?img=https://i.ibb.co/yngBszVt/20250330-213932.png", 
  "type":"x" 
}
]
}
